LICENSE
MANIFEST.in
README.md
setup.py
wagtail_jinja2/__init__.py
wagtail_jinja2/extensions.py
wagtail_jinja2.egg-info/PKG-INFO
wagtail_jinja2.egg-info/SOURCES.txt
wagtail_jinja2.egg-info/dependency_links.txt
wagtail_jinja2.egg-info/not-zip-safe
wagtail_jinja2.egg-info/requires.txt
wagtail_jinja2.egg-info/top_level.txt