Metadata-Version: 1.1
Name: wagtail-jinja2
Version: 0.1.2
Summary: Jinja2 extensions to support the main django tags on wagtail.
Home-page: https://github.com/minervaproject/wagtail-jinja2
Author: Arthur Rio
Author-email: arthur@minervaproject.com
License: MIT
Platform: UNKNOWN
Classifier: Development Status :: 5 - Production/Stable
Classifier: Environment :: Web Environment
Classifier: Intended Audience :: Developers
Classifier: License :: OSI Approved :: MIT License
Classifier: Operating System :: OS Independent
Classifier: Programming Language :: Python
Classifier: Programming Language :: Python :: 2
Classifier: Programming Language :: Python :: 2.7
Classifier: Programming Language :: Python :: 3
Classifier: Programming Language :: Python :: 3.3
Classifier: Programming Language :: Python :: 3.4
Classifier: Framework :: Django
Classifier: Topic :: Software Development :: Libraries :: Python Modules
